dm_app/__init__.py
dm_app/authz/__init__.py
dm_app/authz/admin.py
dm_app/authz/apps.py
dm_app/authz/errors.py
dm_app/authz/managers.py
dm_app/authz/models.py
dm_app/authz/serializers.py
dm_app/authz/service.py
dm_app/authz/urls.py
dm_app/authz/views.py
dm_app/authz/migrations/0001_initial.py
dm_app/authz/migrations/__init__.py
dm_app/authz/tests/__init__.py
dm_app_authz-1.0.1.dist-info/licenses/LICENSE
dm_app_authz-1.0.1.dist-info/METADATA
dm_app_authz-1.0.1.dist-info/WHEEL
dm_app_authz-1.0.1.dist-info/top_level.txt
dm_app_authz-1.0.1.dist-info/RECORD
